[{"summer": true, "name": "Animal Production Topics", "spring": true, "number": "SVM  510", "descripton": "Students will be provided with experience in management of production animals with an emphasis on the veterinary aspects of population health. Experience will come in the form of hands-on experiences and working through relevant literature to specific and relevant population health issues.", "fall": true, "units": " 1-3"}, {"summer": true, "name": "Advanced Specialty Training", "spring": true, "number": "SVM  579", "descripton": "This course is designed to give students clinical experience and training to understand basic health management strategies, handle clinical evaluations, use diagnostic tools to facilitate accurate diagnosis, and develop prevention and/or treatment plans for health management. This course is restricted to Students in the SVM program.", "fall": true, "units": " 1-3"}, {"summer": false, "name": "Special Topics", "spring": true, "number": "SVM  595", "fall": true, "units": " 1-3"}, {"summer": "True", "name": "Seminar", "spring": "True", "number": "SVM  601", "fall": "True", "units": " 1-3"}, {"summer": "True", "name": "Seminar - Poultry Medicine", "spring": "True", "number": "SVM  602", "fall": "True", "units": " 1-3"}, {"summer": "True", "name": "Seminar - Small Animal Surgery", "spring": "True", "number": "SVM  603", "fall": "True", "units": " 1-3"}, {"summer": "True", "name": "Special Topics", "spring": "True", "number": "SVM  610", "fall": "True", "units": " 1-3"}, {"summer": "True", "name": "Advanced Animal Production Topics", "prerequisites": "Prerequisite: SVM 510", "spring": "True", "number": "SVM  615", "descripton": "Course is restricted to students in the SVM program", "fall": "True", "units": " 1-3"}, {"summer": "True", "name": "Advanced Reading", "spring": "True", "number": "SVM  635", "fall": "True", "units": " 1-3"}, {"summer": "True", "name": "Internship - SVM", "spring": "True", "number": "SVM  650", "fall": "True", "units": " 1-3"}, {"summer": "True", "name": "Supervise Teaching", "spring": "True", "number": "SVM  685", "fall": "True", "units": " 1-3"}, {"summer": "True", "name": "Other Teaching", "spring": "True", "number": "SVM  686", "fall": "True", "units": " 1-3"}, {"summer": "True", "name": "Supervised Research", "spring": "True", "number": "SVM  693", "fall": "True", "units": " 1-3"}]